MANIFEST.in
README.rst
setup.py
parallel_queue/__init__.py
parallel_queue/tests.py
parallel_queue.egg-info/PKG-INFO
parallel_queue.egg-info/SOURCES.txt
parallel_queue.egg-info/dependency_links.txt
parallel_queue.egg-info/not-zip-safe
parallel_queue.egg-info/top_level.txt