Metadata-Version: 1.1
Name: parallel-queue
Version: 0.5
Summary: A multi-process task queue that maintains FIFO order.
Home-page: UNKNOWN
Author: Tikitu de Jager
Author-email: tikitu@logophile.org
License: UNKNOWN
Platform: UNKNOWN
Classifier: Development Status :: 4 - Beta
Classifier: License :: OSI Approved :: MIT License
Classifier: Programming Language :: Python :: 2.7
Classifier: Operating System :: OS Independent
Classifier: Topic :: Utilities
